{
  "code": "0",
  "data": [
    {
      "kaNo": "001",
      "kaName": "局・部 1",
      "listKaChild": [
        {
          "kaNo": "001001",
          "kaName": "局・部 1-1",
          "listKaChild": []
        },
        {
          "kaNo": "001002",
          "kaName": "局・部 1-2",
          "listKaChild": []
        }
      ]
    },
    {
      "kaNo": "002",
      "kaName": "局・部 2",
      "listKaChild": [
        {
          "kaNo": "002001",
          "kaName": "局・部 2-1",
          "listKaChild": []
        },
        {
          "kaNo": "002002",
          "kaName": "局・部 2-2",
          "listKaChild": []
        }
      ]
    }
  ]
}